djask/__init__.py
djask/__main__.py
djask/admin/__init__.py
djask/admin/api/__init__.py
djask/admin/api/decorators.py
djask/admin/api/schemas.py
djask/admin/api/views.py
djask/admin/cli.py
djask/admin/ext.py
djask/admin/ui/__init__.py
djask/admin/ui/decorators.py
djask/admin/ui/forms.py
djask/admin/ui/views.py
djask/app.py
djask/auth/__init__.py
djask/auth/abstract.py
djask/auth/anonymous.py
djask/auth/models.py
djask/blueprints.py
djask/cli.py
djask/custom_commands.py
djask/db/__init__.py
djask/db/models.py
djask/exceptions.py
djask/extensions.py
djask/globals.py
djask/helpers.py
djask/mixins.py
djask/project_template/cookiecutter-djask/.git
djask/project_template/cookiecutter-djask/.gitignore
djask/project_template/cookiecutter-djask/LICENSE
djask/project_template/cookiecutter-djask/README.md
djask/project_template/cookiecutter-djask/cookiecutter.json
djask/project_template/cookiecutter-djask/{{cookiecutter.app_name}}/README.md
djask/project_template/cookiecutter-djask/{{cookiecutter.app_name}}/requirements/dev.in
djask/project_template/cookiecutter-djask/{{cookiecutter.app_name}}/requirements/production.in
djask/project_template/cookiecutter-djask/{{cookiecutter.app_name}}/tests/__init__.py
djask/project_template/cookiecutter-djask/{{cookiecutter.app_name}}/tests/conftest.py
djask/project_template/cookiecutter-djask/{{cookiecutter.app_name}}/wsgi.py
djask/project_template/cookiecutter-djask/{{cookiecutter.app_name}}/{{cookiecutter.app_name}}/__init__.py
djask/project_template/cookiecutter-djask/{{cookiecutter.app_name}}/{{cookiecutter.app_name}}/settings.py
djask/project_template/cookiecutter-djask/{{cookiecutter.app_name}}/{{cookiecutter.app_name}}/templates/base.html
djask/project_template/cookiecutter-djask-bp/.git
djask/project_template/cookiecutter-djask-bp/.gitignore
djask/project_template/cookiecutter-djask-bp/LICENSE
djask/project_template/cookiecutter-djask-bp/cookiecutter.json
Djask-0.6.2.dist-info/entry_points.txt
Djask-0.6.2.dist-info/WHEEL
Djask-0.6.2.dist-info/METADATA
Djask-0.6.2.dist-info/license_files/LICENSE
Djask-0.6.2.dist-info/RECORD
