Metadata-Version: 2.1
Name: Djask
Version: 0.6.2
Summary: An enhanced django-like Flask
License: MIT
Keywords: flask,apiflask
Author-email: andyzhou <andyforever0108@outlook.com>
Requires-Python: >=3.8
Classifier: Development Status :: 3 - Alpha
Classifier: Environment :: Web Environment
Classifier: Framework :: Flask
Classifier: Intended Audience :: Developers
Classifier: License :: OSI Approved :: MIT License
Classifier: Operating System :: OS Independent
Classifier: Programming Language :: Python :: 3.10
Classifier: Programming Language :: Python :: 3.7
Classifier: Programming Language :: Python :: 3.8
Classifier: Programming Language :: Python :: 3.9
Classifier: Topic :: Internet :: WWW/HTTP
Classifier: Topic :: Internet :: WWW/HTTP :: Dynamic Content
Classifier: Topic :: Internet :: WWW/HTTP :: WSGI
Classifier: Topic :: Internet :: WWW/HTTP :: WSGI :: Application
Requires-Dist: apiflask>=1.1.1
Requires-Dist: authlib>=1.0.1
Requires-Dist: bootstrap-flask~=2.0
Requires-Dist: colorama>=0.4.5
Requires-Dist: cookiecutter>=1.7.3
Requires-Dist: flask-compress~=1.10
Requires-Dist: flask-login~=0.5
Requires-Dist: flask-sqlalchemy~=2.5
Requires-Dist: flask-wtf~=0.15
Requires-Dist: flask>=2.2.0
Requires-Dist: marshmallow-sqlalchemy>=0.27.0
Requires-Dist: python-dotenv>=0.19.2
Requires-Dist: wtforms-sqlalchemy~=0.3
Project-URL: Documentation, https://djask.readthedocs.io
Project-URL: Home, https://github.com/z-t-y/djask
Project-URL: Repo, https://github.com/z-t-y/djask
